[
 {
  "title": "A Light in the Attic",
  "old_price_gbp": 51.77,
  "new_price_kes": 9064.45
 },
 {
  "title": "Tipping the Velvet",
  "old_price_gbp": 53.74,
  "new_price_kes": 9409.37
 },
 {
  "title": "Soumission",
  "old_price_gbp": 50.1,
  "new_price_kes": 8772.04
 },
 {
  "title": "Sharp Objects",
  "old_price_gbp": 47.82,
  "new_price_kes": 8372.84
 },
 {
  "title": "Sapiens: A Brief History of Humankind",
  "old_price_gbp": 54.23,
  "new_price_kes": 9495.17
 },
 {
  "title": "The Requiem Red",
  "old_price_gbp": 22.65,
  "new_price_kes": 3965.8
 },
 {
  "title": "The Dirty Little Secrets of Getting Your Dream Job",
  "old_price_gbp": 33.34,
  "new_price_kes": 5837.52
 },
 {
  "title": "The Coming Woman: A Novel Based on the Life of the Infamous Feminist, Victoria Woodhull",
  "old_price_gbp": 17.93,
  "new_price_kes": 3139.38
 },
 {
  "title": "The Boys in the Boat: Nine Americans and Their Epic Quest for Gold at the 1936 Berlin Olympics",
  "old_price_gbp": 22.6,
  "new_price_kes": 3957.05
 },
 {
  "title": "The Black Maria",
  "old_price_gbp": 52.15,
  "new_price_kes": 9130.98
 },
 {
  "title": "Starving Hearts (Triangular Trade Trilogy, #1)",
  "old_price_gbp": 13.99,
  "new_price_kes": 2449.52
 },
 {
  "title": "Shakespeare's Sonnets",
  "old_price_gbp": 20.66,
  "new_price_kes": 3617.37
 },
 {
  "title": "Set Me Free",
  "old_price_gbp": 17.46,
  "new_price_kes": 3057.08
 },
 {
  "title": "Scott Pilgrim's Precious Little Life (Scott Pilgrim #1)",
  "old_price_gbp": 52.29,
  "new_price_kes": 9155.49
 },
 {
  "title": "Rip it Up and Start Again",
  "old_price_gbp": 35.02,
  "new_price_kes": 6131.68
 }
]